test_package_pigeon/__init__.py
test_package_pigeon/module.py
test_package_pigeon-0.0.1.dist-info/METADATA
test_package_pigeon-0.0.1.dist-info/WHEEL
test_package_pigeon-0.0.1.dist-info/top_level.txt
test_package_pigeon-0.0.1.dist-info/RECORD
